pip_aide/__init__.py
pip_aide/cli.py
pip_aide-1.0.2.dist-info/licenses/LICENSE
pip_aide-1.0.2.dist-info/METADATA
pip_aide-1.0.2.dist-info/WHEEL
pip_aide-1.0.2.dist-info/entry_points.txt
pip_aide-1.0.2.dist-info/top_level.txt
pip_aide-1.0.2.dist-info/RECORD
